what3words/__init__.py
what3words/version.py
what3words/what3words.py
what3words-3.4.0.dist-info/LICENSE
what3words-3.4.0.dist-info/METADATA
what3words-3.4.0.dist-info/WHEEL
what3words-3.4.0.dist-info/top_level.txt
what3words-3.4.0.dist-info/RECORD
